{"is_source_file": true, "format": "Dart", "description": "This file is a Flutter application's main entry point, defining the app widget and home page with a simple centered progress indicator.", "external_files": ["package:flutter/material.dart"], "external_methods": [], "published": ["main", "MyApp", "MyHomePage", "_MyHomePageState"], "classes": [{"name": "MyApp", "description": "Stateless widget that sets up the MaterialApp with theme and home page."}, {"name": "MyHomePage", "description": "Stateful widget representing the home page with a title."}, {"name": "_MyHomePageState", "description": "State class for MyHomePage that builds the scaffold with app bar and centered content."}], "methods": [{"name": "main", "description": "Entry point of the Flutter application, runs MyApp."}, {"name": "build (MyApp)", "description": "Builds the MaterialApp widget with theme and home page."}, {"name": "build (MyHomePage)", "description": "Builds the home page's scaffold containing app bar and body."}, {"name": "build (_MyHomePageState)", "description": "Returns the widget tree for the home page with a progress indicator."}], "calls": ["runApp", "MaterialApp", "ThemeData", "ColorScheme.fromSeed", "Colors.blue", "Theme.of", "Scaffold", "AppBar", "Text", "Center", "Column", "mainAxisAlignment", "Text", "TextStyle", "SizedBox", "CircularProgressIndicator"], "search-terms": ["Flutter", "main.dart", "StatelessWidget", "StatefulWidget", "MaterialApp", "Scaffold", "ProgressIndicator", "home page", "app bar", "theme", "ui layout"], "state": 2, "file_id": 1, "knowledge_revision": 9, "git_revision": "", "hash": "16b3d43a0dc4410bebe825d2e4d7c413", "format-version": 4, "code-base-name": "frontend_react", "filename": "frontend_react/lib/main.dart", "revision_history": [{"9": ""}]}